lobsterpy/__init__.py
lobsterpy/cli.py
lobsterpy/cohp/__init__.py
lobsterpy/cohp/analyze.py
lobsterpy/cohp/describe.py
lobsterpy/featurize/__init__.py
lobsterpy/featurize/batch.py
lobsterpy/featurize/core.py
lobsterpy/featurize/utils.py
lobsterpy/plotting/__init__.py
lobsterpy/plotting/layout_dicts.py
lobsterpy/plotting/lobsterpy_base.mplstyle
lobsterpy/structuregraph/__init__.py
lobsterpy/structuregraph/graph.py
lobsterpy-0.5.8.dist-info/licenses/LICENSE
lobsterpy-0.5.8.dist-info/METADATA
lobsterpy-0.5.8.dist-info/WHEEL
lobsterpy-0.5.8.dist-info/entry_points.txt
lobsterpy-0.5.8.dist-info/top_level.txt
lobsterpy-0.5.8.dist-info/RECORD
