Metadata-Version: 2.4
Name: lobsterpy
Version: 0.5.8
Summary: Package for automatic bonding analysis with Lobster/VASP
Author-email: Janine George <janine.george@bam.de>
License: BSD 3-Clause
Project-URL: homepage, https://jageo.github.io/LobsterPy/
Project-URL: repository, https://github.com/JaGeo/LobsterPy
Project-URL: documentation, https://jageo.github.io/LobsterPy/
Project-URL: changelog, https://jageo.github.io/LobsterPy/about/changelog.html
Keywords: high-throughput,automated,lobsteroutput,bonding-analysis
Classifier: Programming Language :: Python :: 3
Classifier: Programming Language :: Python :: 3.10
Classifier: Programming Language :: Python :: 3.11
Classifier: Programming Language :: Python :: 3.12
Classifier: Development Status :: 5 - Production/Stable
Classifier: Intended Audience :: Science/Research
Classifier: Operating System :: OS Independent
Requires-Python: <3.13,>=3.10
License-File: LICENSE
Requires-Dist: pymatgen>=2024.10.22
Requires-Dist: numpy<3.0.0
Provides-Extra: featurizer
Requires-Dist: mendeleev==1.1.0; extra == "featurizer"
Provides-Extra: dev
Requires-Dist: pre-commit>=2.12.1; extra == "dev"
Provides-Extra: tests
Requires-Dist: pytest; extra == "tests"
Requires-Dist: pytest-mock; extra == "tests"
Requires-Dist: pytest-split; extra == "tests"
Requires-Dist: pytest-cov; extra == "tests"
Requires-Dist: types-setuptools; extra == "tests"
Provides-Extra: docs
Requires-Dist: sphinx-copybutton==0.5.2; extra == "docs"
Requires-Dist: sphinx<9,>=5; extra == "docs"
Requires-Dist: sphinx_design==0.6.1; extra == "docs"
Requires-Dist: myst-nb==1.3.0; extra == "docs"
Requires-Dist: sphinx-book-theme==1.1.4; extra == "docs"
Requires-Dist: sphinx-argparse==0.5.2; extra == "docs"
Requires-Dist: sphinx-toolbox==4.1.1; extra == "docs"
Dynamic: license-file
